{"version":"0.1.0","name":"Clickhouse Storage","tags":["Database"],"tiles":[{"id":"4p9uqprcgot4izb25282a3","x":0,"y":6,"w":8,"h":6,"config":{"displayType":"number","numberFormat":{"output":"number","mantissa":2,"thousandSeparated":true,"average":false,"decimalBytes":false,"factor":1},"granularity":"auto","compareToPreviousPeriod":false,"fillNulls":0,"alignDateRangeToGranularity":true,"configType":"sql","sqlTemplate":"SELECT\n    round(\n        sum(data_uncompressed_bytes)\n        / nullIf(sum(data_compressed_bytes), 0),\n        2\n    ) AS compression_ratio\nFROM system.parts\nWHERE active = 1;","connection":"Local ClickHouse","source":"Logs","name":"압축률"},"containerId":"i83407o5qid8xh8zkdr6is","tabId":"b9os997luky8yzthbk4n"},{"id":"ljx7tzrjkci1ie3afvzte","x":16,"y":0,"w":8,"h":10,"config":{"displayType":"pie","numberFormat":{"output":"byte","numericUnit":"bytes_iec","mantissa":2,"thousandSeparated":true,"average":false,"decimalBytes":false,"factor":1},"granularity":"auto","compareToPreviousPeriod":false,"fillNulls":0,"alignDateRangeToGranularity":true,"configType":"sql","sqlTemplate":"SELECT\n    if(active, 'active', 'inactive'),\n    sum(bytes_on_disk) AS size\nFROM system.parts\nGROUP BY active;","connection":"Local ClickHouse","source":"Logs","name":"active/inactive 디스크 사용량 (parts)"},"containerId":"pto5oi98rdgiwycrikn79","tabId":"1rk81y2jpb1u2iltywoihi"},{"id":"afsme4064usfa924ahqnav","x":8,"y":0,"w":8,"h":10,"config":{"displayType":"pie","numberFormat":{"output":"byte","numericUnit":"bytes_iec","mantissa":2,"thousandSeparated":true,"average":false,"decimalBytes":false,"factor":1},"granularity":"auto","compareToPreviousPeriod":false,"fillNulls":0,"alignDateRangeToGranularity":true,"configType":"sql","sqlTemplate":"SELECT\n    database || '.' ||  table,\n    sum(bytes_on_disk) AS bytes_on_disk\nFROM system.parts\nGROUP BY\n    database,\n    table","connection":"Local ClickHouse","source":"Logs","name":"테이블별 디스크 사용량 (parts)"},"containerId":"pto5oi98rdgiwycrikn79","tabId":"1rk81y2jpb1u2iltywoihi"},{"id":"4wqkyg9tnmxo4vbiodis5r","x":0,"y":0,"w":8,"h":10,"config":{"displayType":"pie","numberFormat":{"output":"byte","numericUnit":"bytes_iec","mantissa":2,"thousandSeparated":true,"average":false,"decimalBytes":false,"factor":1},"granularity":"auto","compareToPreviousPeriod":false,"fillNulls":0,"alignDateRangeToGranularity":true,"configType":"sql","sqlTemplate":"SELECT\n    database,\n    sum(bytes_on_disk) AS bytes_on_disk\nFROM system.parts\nGROUP BY\n    database","connection":"Local ClickHouse","source":"Logs","name":"DB별 디스크 사용량 (parts)"},"containerId":"pto5oi98rdgiwycrikn79","tabId":"1rk81y2jpb1u2iltywoihi"},{"id":"xs0fodsyqd8k0rea1g459","x":8,"y":0,"w":8,"h":6,"config":{"displayType":"number","numberFormat":{"output":"byte","numericUnit":"bytes_iec","mantissa":2,"thousandSeparated":true,"average":false,"decimalBytes":false,"factor":1},"granularity":"auto","compareToPreviousPeriod":false,"fillNulls":0,"alignDateRangeToGranularity":true,"configType":"sql","sqlTemplate":"SELECT\n    sum(data_uncompressed_bytes) AS size\nFROM system.parts\n","connection":"Local ClickHouse","source":"Logs","name":"미압축시 원본 디스크 크기 (parts)"},"containerId":"i83407o5qid8xh8zkdr6is","tabId":"b9os997luky8yzthbk4n"},{"id":"gbldxfzs1gqatfznijww9","x":16,"y":0,"w":8,"h":6,"config":{"displayType":"number","numberFormat":{"output":"number","mantissa":2,"thousandSeparated":true,"average":true,"decimalBytes":false,"factor":1},"granularity":"auto","compareToPreviousPeriod":false,"fillNulls":0,"alignDateRangeToGranularity":true,"configType":"sql","sqlTemplate":"SELECT\n    sum(rows) AS total_rows\nFROM system.parts","connection":"Local ClickHouse","source":"Logs","name":"전체 데이터 행 (parts)"},"containerId":"i83407o5qid8xh8zkdr6is","tabId":"b9os997luky8yzthbk4n"},{"id":"tyvip0e45ui2zx80nk7qxu","x":8,"y":6,"w":8,"h":6,"config":{"displayType":"number","numberFormat":{"output":"percent","mantissa":2,"thousandSeparated":true,"average":true,"decimalBytes":false,"factor":1},"granularity":"auto","compareToPreviousPeriod":false,"fillNulls":0,"alignDateRangeToGranularity":true,"configType":"sql","sqlTemplate":"select\n\tsumIf(bytes_on_disk, active = 0) \n\t/ \n\tsum(bytes_on_disk)\n    as dead_part_percent\nFROM system.parts;","connection":"Local ClickHouse","source":"Logs","name":"dead parts 비율 (parts)"},"containerId":"i83407o5qid8xh8zkdr6is","tabId":"b9os997luky8yzthbk4n"},{"id":"2wqf98zttfn10yuc16efona","x":0,"y":0,"w":8,"h":6,"config":{"displayType":"number","numberFormat":{"output":"byte","numericUnit":"bytes_iec","mantissa":2,"thousandSeparated":true,"average":false,"decimalBytes":false,"factor":1},"granularity":"auto","compareToPreviousPeriod":false,"fillNulls":0,"alignDateRangeToGranularity":true,"configType":"sql","sqlTemplate":"SELECT\n    sum(bytes_on_disk) AS size\nFROM system.parts\n","connection":"Local ClickHouse","source":"Logs","name":"현재 사용 공간 (parts)"},"containerId":"i83407o5qid8xh8zkdr6is","tabId":"b9os997luky8yzthbk4n"}],"filters":[],"containers":[{"id":"i83407o5qid8xh8zkdr6is","title":"전체 수치","collapsed":false,"tabs":[{"id":"b9os997luky8yzthbk4n","title":"전체 수치"}]},{"id":"pto5oi98rdgiwycrikn79","title":"그래프","collapsed":false,"tabs":[{"id":"1rk81y2jpb1u2iltywoihi","title":"그래프"}]}]}